aperampimsrequests/__init__.py
aperampimsrequests/escrever_valor_tag_pims.py
aperampimsrequests/obter_dados_pims_batch.py
aperampimsrequests-0.2.1.dist-info/METADATA
aperampimsrequests-0.2.1.dist-info/WHEEL
aperampimsrequests-0.2.1.dist-info/RECORD
