Metadata-Version: 2.4
Name: aperampimsrequests
Version: 0.2.1
Summary: Helpers para ler/escrever no PIMS da Aperam
Author: senrajudson
Requires-Python: >=3.12
Classifier: Programming Language :: Python :: 3
Classifier: Programming Language :: Python :: 3.12
Classifier: Programming Language :: Python :: 3.13
Classifier: Programming Language :: Python :: 3.14
Requires-Dist: pandas (>=2.3.3,<3.0.0)
Requires-Dist: requests (>=2.32.5,<3.0.0)
